detect_direct_checkins.py
detect_direct_checkins-0.1.2.dist-info/LICENSE
detect_direct_checkins-0.1.2.dist-info/METADATA
detect_direct_checkins-0.1.2.dist-info/WHEEL
detect_direct_checkins-0.1.2.dist-info/entry_points.txt
detect_direct_checkins-0.1.2.dist-info/top_level.txt
detect_direct_checkins-0.1.2.dist-info/RECORD
