Metadata-Version: 2.1
Name: detect-direct-checkins
Version: 0.1.2
Summary: A utility which detects direct checkins on specific branches.
Home-page: https://github.com/IngoMeyer441/detect-direct-checkins
Author: Ingo Meyer
Author-email: i.meyer@fz-juelich.de
License: MIT
Keywords: pre-commit,git,merge-commit
Platform: UNKNOWN
Classifier: Development Status :: 5 - Production/Stable
Classifier: Intended Audience :: Developers
Classifier: License :: OSI Approved :: MIT License
Classifier: Natural Language :: English
Classifier: Operating System :: MacOS
Classifier: Operating System :: POSIX :: BSD
Classifier: Operating System :: POSIX :: Linux
Classifier: Programming Language :: Python
Classifier: Programming Language :: Python :: 3
Classifier: Programming Language :: Python :: 3 :: Only
Classifier: Programming Language :: Python :: 3.5
Classifier: Programming Language :: Python :: 3.6
Classifier: Programming Language :: Python :: 3.7
Classifier: Programming Language :: Python :: 3.8
Classifier: Programming Language :: Python :: 3.9
Classifier: Programming Language :: Python :: 3.10
Classifier: Topic :: Software Development :: Version Control :: Git
Classifier: Topic :: Utilities
Requires-Python: ~=3.5
License-File: LICENSE
